<?xml version="1.0" encoding="utf-8"?>
<publishData>
  <publishProfile publishUrl="C:\temp\inti" deleteExistingFiles="True" ftpAnonymousLogin="False" ftpPassiveMode="True" msdeploySite="" msdeploySiteID="" msdeployRemoteSitePhysicalPath="" msdeployAllowUntrustedCertificate="False" msdeploySkipExtraFilesOnServer="True" msdeployMarkAsApp="False" profileName="Profile1" publishMethod="FileSystem" replaceMatchingFiles="False" userName="" savePWD="False" userPWD="" SelectedForPublish="True">
    <file relUrl="inti2008.Master" publishTime="07/30/2012 11:49:43" />
    <file relUrl="Default.aspx" publishTime="08/20/2009 13:40:40" />
    <file relUrl="AdminEditNews.aspx" publishTime="06/05/2012 10:53:01" />
    <file relUrl="Standing.aspx" publishTime="08/17/2009 09:10:53" />
    <file relUrl="img/flag_red.gif" publishTime="08/11/2008 11:30:00" />
    <file relUrl="bin/inti2008.Data.dll" publishTime="08/18/2012 15:33:01" />
    <file relUrl="AdminPlayerImport.aspx" publishTime="07/28/2009 21:46:57" />
    <file relUrl="img/header.gif" publishTime="09/25/2008 22:50:49" />
    <file relUrl="UploadImage.ascx" publishTime="01/19/2009 16:25:16" />
    <file relUrl="Web.config" publishTime="06/06/2012 14:12:19" />
    <file relUrl="TeamView.ascx" publishTime="07/20/2008 15:31:56" />
    <file relUrl="Scripts/jquery-1.7.2.min.js" publishTime="06/06/2012 14:12:16" />
    <file relUrl="AdminTournamentList.aspx" publishTime="10/15/2008 13:32:20" />
    <file relUrl="bin/MiniProfiler.pdb" publishTime="06/06/2012 13:41:22" />
    <file relUrl="SignIn.aspx" publishTime="07/26/2008 17:04:00" />
    <file relUrl="UserMessages.aspx" publishTime="06/05/2012 13:10:14" />
    <file relUrl="MyTournamentEdit.aspx" publishTime="10/15/2008 13:35:35" />
    <file relUrl="bin/System.Web.Silverlight.dll" publishTime="10/08/2008 16:49:38" />
    <file relUrl="Error.aspx" publishTime="07/26/2008 17:02:59" />
    <file relUrl="MatchView.aspx" publishTime="07/26/2008 17:03:25" />
    <file relUrl="ForumViewThreads.aspx" publishTime="10/15/2008 12:03:24" />
    <file relUrl="ForgotPassword.aspx" publishTime="07/26/2008 17:02:57" />
    <file relUrl="PlayerView.aspx" publishTime="08/18/2009 13:18:58" />
    <file relUrl="bin/inti2008.Web.dll" publishTime="08/18/2012 15:33:02" />
    <file relUrl="bin/AjaxControlToolkit.dll" publishTime="06/30/2008 08:54:32" />
    <file relUrl="Scripts/jquery-1.7.2.js" publishTime="06/06/2012 14:12:16" />
    <file relUrl="AdminEditUser.aspx" publishTime="08/19/2009 14:09:13" />
    <file relUrl="bin/System.Drawing.dll" publishTime="03/18/2010 18:31:26" />
    <file relUrl="img/flag_white.gif" publishTime="08/11/2008 11:30:16" />
    <file relUrl="UserSettings.aspx" publishTime="07/26/2008 17:02:23" />
    <file relUrl="media/Nyheter.wmv" publishTime="08/17/2009 15:56:49" />
    <file relUrl="App_Themes/default/img/stands.jpg" publishTime="07/11/2008 19:14:14" />
    <file relUrl="MyTournamentStanding.aspx" publishTime="10/15/2008 13:43:46" />
    <file relUrl="News.aspx" publishTime="08/20/2009 13:57:32" />
    <file relUrl="bin/MiniProfiler.dll" publishTime="06/06/2012 13:41:22" />
    <file relUrl="TournamentStanding.ascx" publishTime="12/17/2008 10:37:17" />
    <file relUrl="menu.ascx" publishTime="06/25/2012 22:11:51" />
    <file relUrl="img/arrow_down.gif" publishTime="08/11/2008 11:31:45" />
    <file relUrl="TeamView.aspx" publishTime="10/17/2009 13:14:47" />
    <file relUrl="media/Matchuppdatering.wmv" publishTime="08/17/2009 14:20:24" />
    <file relUrl="PrivateTournaments.ascx" publishTime="01/19/2009 10:13:30" />
    <file relUrl="img/grdback.png" publishTime="07/26/2008 15:35:44" />
    <file relUrl="img/email_open.png" publishTime="08/17/2009 13:29:10" />
    <file relUrl="ForumViewThread.aspx" publishTime="10/15/2008 12:04:21" />
    <file relUrl="img/arrow_left.gif" publishTime="08/11/2008 11:32:04" />
    <file relUrl="img/bggrad.gif" publishTime="07/31/2010 13:26:57" />
    <file relUrl="AdminPlayerList.aspx" publishTime="08/05/2009 13:32:53" />
    <file relUrl="MessageCreate.aspx" publishTime="10/15/2008 13:45:00" />
    <file relUrl="img/icon_alert.gif" publishTime="08/11/2008 11:34:11" />
    <file relUrl="img/red_flag.png" publishTime="08/03/2008 19:23:05" />
    <file relUrl="img/green_check.png" publishTime="08/03/2008 19:23:44" />
    <file relUrl="packages.config" publishTime="06/06/2012 14:12:16" />
    <file relUrl="AdminMain.aspx" publishTime="06/21/2012 08:31:54" />
    <file relUrl="img/eurobg.jpg" publishTime="06/03/2012 21:12:03" />
    <file relUrl="AdminApproveUserTeams.aspx" publishTime="07/04/2012 20:32:19" />
    <file relUrl="bin/inti2008.Data.pdb" publishTime="08/18/2012 15:33:01" />
    <file relUrl="img/flag_green.gif" publishTime="08/11/2008 11:29:20" />
    <file relUrl="ViewChangeLog.ascx" publishTime="11/24/2008 22:30:47" />
    <file relUrl="img/email.png" publishTime="08/17/2009 12:53:10" />
    <file relUrl="img/bg.png" publishTime="07/30/2012 11:47:28" />
    <file relUrl="AdminPlayerEdit.aspx" publishTime="08/05/2009 13:13:28" />
    <file relUrl="ForumEntries.ascx" publishTime="12/17/2008 14:44:03" />
    <file relUrl="PrivateTournaments.aspx" publishTime="01/19/2009 09:58:48" />
    <file relUrl="SignUp.aspx" publishTime="07/27/2008 22:21:02" />
    <file relUrl="PlayerSelector.aspx" publishTime="07/27/2008 15:40:40" />
    <file relUrl="img/action_stop.gif" publishTime="08/11/2008 11:31:20" />
    <file relUrl="img/icon_email.gif" publishTime="08/11/2008 11:34:33" />
    <file relUrl="img/icon_user.gif" publishTime="08/11/2008 11:35:08" />
    <file relUrl="RulesShow.aspx" publishTime="10/15/2008 11:57:57" />
    <file relUrl="img/arrow_right.gif" publishTime="08/11/2008 11:32:25" />
    <file relUrl="img/icon_accept.gif" publishTime="08/11/2008 11:30:38" />
    <file relUrl="AdminBatchEditMatches.aspx" publishTime="08/18/2012 15:15:54" />
    <file relUrl="UserTeamUploadImage.aspx" publishTime="01/19/2009 16:20:01" />
    <file relUrl="DaySelector.ascx" publishTime="11/24/2008 22:37:50" />
    <file relUrl="AdminUpdateMatch.aspx" publishTime="06/05/2012 12:43:18" />
    <file relUrl="UserView.aspx" publishTime="07/27/2008 22:19:20" />
    <file relUrl="MessageView.aspx" publishTime="10/15/2008 13:45:16" />
    <file relUrl="media/Professional.xaml" publishTime="08/17/2009 14:07:46" />
    <file relUrl="img/gradientButton.png" publishTime="07/26/2008 17:06:31" />
    <file relUrl="ChangePassword.aspx" publishTime="07/26/2008 17:03:01" />
    <file relUrl="MediaPlayer.aspx" publishTime="08/17/2009 15:44:16" />
    <file relUrl="img/comment_yellow.gif" publishTime="08/11/2008 11:33:12" />
    <file relUrl="img/flag_orange.gif" publishTime="08/11/2008 11:29:37" />
    <file relUrl="Scripts/jquery-1.7.2-vsdoc.js" publishTime="06/06/2012 14:12:16" />
    <file relUrl="img/arrow_up.gif" publishTime="08/11/2008 11:32:44" />
    <file relUrl="AdminTournamentEdit.aspx" publishTime="08/18/2012 15:13:24" />
    <file relUrl="bin/inti2008.Web.pdb" publishTime="08/18/2012 15:33:02" />
    <file relUrl="UserTeamView.aspx" publishTime="06/05/2012 13:32:05" />
    <file relUrl="AdminEditMatch.aspx" publishTime="08/18/2012 14:37:45" />
    <file relUrl="AdminEditRules.aspx" publishTime="06/04/2012 20:01:06" />
    <file relUrl="AdminEditClub.aspx" publishTime="07/26/2008 17:03:13" />
    <file relUrl="PlayerList.aspx" publishTime="07/28/2009 13:48:35" />
    <file relUrl="img/redGradientButton.png" publishTime="11/12/2008 11:02:54" />
    <file relUrl="bin/MiniProfiler.xml" publishTime="06/06/2012 13:41:22" />
    <file relUrl="UserTeamEdit.aspx" publishTime="07/31/2009 14:28:43" />
    <file relUrl="Global.asax" publishTime="04/13/2008 13:40:52" />
    <file relUrl="Rss.ascx" publishTime="12/17/2008 16:11:43" />
    <file relUrl="TournamentSelector.ascx" publishTime="07/28/2009 22:05:39" />
    <file relUrl="Completion.asmx" publishTime="07/26/2008 17:28:56" />
  </publishProfile>
</publishData>